lektor_expression_type.py
lektor_expression_type-0.1.dist-info/LICENSE
lektor_expression_type-0.1.dist-info/METADATA
lektor_expression_type-0.1.dist-info/WHEEL
lektor_expression_type-0.1.dist-info/entry_points.txt
lektor_expression_type-0.1.dist-info/top_level.txt
lektor_expression_type-0.1.dist-info/RECORD
