Metadata-Version: 2.1
Name: lektor-expression-type
Version: 0.1
Summary: Add jinja-evaluated types to Lektor
Home-page: https://github.com/dairiki/lektor-expression-type/
Author: Jeff Dairiki
Author-email: dairiki@dairiki.org
License: BSD
Keywords: Lektor plugin
Platform: UNKNOWN
Classifier: Development Status :: 5 - Production/Stable
Classifier: Environment :: Plugins
Classifier: Environment :: Web Environment
Classifier: Framework :: Lektor
Classifier: Intended Audience :: Developers
Classifier: License :: OSI Approved :: BSD License
Classifier: Natural Language :: English
Classifier: Programming Language :: Python :: 2
Classifier: Programming Language :: Python :: 2.7
Classifier: Programming Language :: Python :: 3
Classifier: Programming Language :: Python :: 3.6
Classifier: Programming Language :: Python :: 3.7
Classifier: Programming Language :: Python :: 3.8
Classifier: Programming Language :: Python :: 3.9
